<props><contextmenu><group caption="General"><prop caption="menu" editor="textbox" value="[@menu]" description="the id of the menu element."/><prop caption="select" editor="textbox" value="[@select]" description="the xpath executed on the selected element of the databound element which determines whether this contextmenu is shown."/></group><events caption="Events"><prop caption="DOMNodeInserted" editor="textbox" value="[@domnodeinserted]" type="event"/><prop caption="DOMNodeInsertedIntoDocument" editor="textbox" value="[@domnodeinsertedintodocument]" type="event"/><prop caption="DOMNodeRemoved" editor="textbox" value="[@domnoderemoved]" type="event"/><prop caption="DOMNodeRemovedFromDocument" editor="textbox" value="[@domnoderemovedfromdocument]" type="event"/><prop caption="propertychange" editor="textbox" value="[@propertychange]" type="event" description="Fires when a property changes."/></events></contextmenu></props>